{
  "uuid": "edab49c9-6e5c-48fe-9bb3-cb000c8b1461",
  "name": "Briarcliff Market & Deli",
  "website": "https://www.briarcliffdeli.com/",
  "timestamp": "2025-12-08T11:35:29.644460+00:00",
  "found": true,
  "saved_files": [
    {
      "url": "https://briarcliffdeli.net/order-online/",
      "file": "menus/edab49c9-6e5c-48fe-9bb3-cb000c8b1461/view-our-menu.html",
      "status": 200,
      "content_type": "text/html",
      "is_menu_like": true
    },
    {
      "url": "https://www.briarcliffdeli.com/wp-content/uploads/2022/06/Catering-Menu-5-24-22.pdf",
      "file": "menus/edab49c9-6e5c-48fe-9bb3-cb000c8b1461/view-download-our-catering-menu.pdf",
      "status": 200,
      "content_type": "application/pdf",
      "is_menu_like": true
    },
    {
      "url": "https://www.briarcliffdeli.com/wp-content/uploads/2019/08/Cateting-Menu-10-10-2018.pdf",
      "file": "menus/edab49c9-6e5c-48fe-9bb3-cb000c8b1461/catering-parties.pdf",
      "status": 200,
      "content_type": "application/pdf",
      "is_menu_like": true
    },
    {
      "url": "https://www.briarcliffdeli.com/",
      "file": "menus/edab49c9-6e5c-48fe-9bb3-cb000c8b1461/menu.html",
      "status": 200,
      "content_type": "text/html",
      "is_menu_like": true
    },
    {
      "url": "https://www.briarcliffdeli.com/menu",
      "file": "menus/edab49c9-6e5c-48fe-9bb3-cb000c8b1461/menu.html",
      "status": 200,
      "content_type": "text/html",
      "is_menu_like": true
    }
  ],
  "errors": []
}