{
  "uuid": "903d7965-65a6-4c61-bcb0-aaeb97ced035",
  "name": "Kpot Korean BBQ & Hot Pot",
  "website": "https://thekpot.com/location/east-brunswick/",
  "timestamp": "2025-12-08T11:02:46.524840+00:00",
  "found": true,
  "saved_files": [
    {
      "url": "https://thekpot.com/menu/",
      "file": "menus/903d7965-65a6-4c61-bcb0-aaeb97ced035/our-menu.html",
      "status": 200,
      "content_type": "text/html",
      "is_menu_like": true
    },
    {
      "url": "https://thekpot.com/menu",
      "file": "menus/903d7965-65a6-4c61-bcb0-aaeb97ced035/our-menu.html",
      "status": 200,
      "content_type": "text/html",
      "is_menu_like": true
    },
    {
      "url": "https://thekpot.com/location/east-brunswick/",
      "file": "menus/903d7965-65a6-4c61-bcb0-aaeb97ced035/menu.html",
      "status": 200,
      "content_type": "text/html",
      "is_menu_like": true
    },
    {
      "url": "https://thekpot.com/our-menu",
      "file": "menus/903d7965-65a6-4c61-bcb0-aaeb97ced035/our-menu.html",
      "status": 200,
      "content_type": "text/html",
      "is_menu_like": true
    },
    {
      "url": "https://thekpot.com/order-online/menu",
      "file": "menus/903d7965-65a6-4c61-bcb0-aaeb97ced035/order-online-menu.html",
      "status": 200,
      "content_type": "text/html",
      "is_menu_like": true
    }
  ],
  "errors": [
    "error_page:https://order.online/online-ordering/business/KPOT-11862815?pickup=true&utm_source=sdk&visitorId=18ea0c09a953234f8:403",
    "error_page:https://thekpot.com/menus:404",
    "error_page:https://thekpot.com/our-menus:404",
    "error_page:https://thekpot.com/food-menu:404",
    "error_page:https://thekpot.com/food-menus:404",
    "error_page:https://thekpot.com/dinner-menu:404",
    "error_page:https://thekpot.com/lunch-menu:404",
    "error_page:https://thekpot.com/brunch-menu:404",
    "error_page:https://thekpot.com/breakfast-menu:404",
    "error_page:https://thekpot.com/kids-menu:404",
    "error_page:https://thekpot.com/kid-menu:404",
    "error_page:https://thekpot.com/kids:404",
    "error_page:https://thekpot.com/drinks-menu:404",
    "error_page:https://thekpot.com/drink-menu:404",
    "error_page:https://thekpot.com/beverages-menu:404",
    "error_page:https://thekpot.com/beverage-menu:404",
    "error_page:https://thekpot.com/wine-menu:404",
    "error_page:https://thekpot.com/dessert-menu:404",
    "error_page:https://thekpot.com/specials:404",
    "error_page:https://thekpot.com/daily-specials:404",
    "error_page:https://thekpot.com/today-specials:404",
    "error_page:https://thekpot.com/buffet-menu:404",
    "error_page:https://thekpot.com/takeaway-menu:404",
    "error_page:https://thekpot.com/take-out-menu:404",
    "error_page:https://thekpot.com/delivery-menu:404"
  ]
}