{
  "uuid": "23bd5c6b-2464-4c4a-9d2e-6f15cf711989",
  "name": "Hummus Market",
  "website": "http://www.levantinenyc.com/",
  "timestamp": "2025-12-06T14:27:10.685488+00:00",
  "found": true,
  "saved_files": [
    {
      "url": "http://www.levantinenyc.com/menus/breakfast-lunch",
      "file": "menus/23bd5c6b-2464-4c4a-9d2e-6f15cf711989/breakfast-lunch.html",
      "status": 200,
      "content_type": "text/html",
      "is_menu_like": true
    },
    {
      "url": "http://www.levantinenyc.com/menus/brunch",
      "file": "menus/23bd5c6b-2464-4c4a-9d2e-6f15cf711989/brunch.html",
      "status": 200,
      "content_type": "text/html",
      "is_menu_like": true
    },
    {
      "url": "http://www.levantinenyc.com/menus/dinner",
      "file": "menus/23bd5c6b-2464-4c4a-9d2e-6f15cf711989/dinner.html",
      "status": 200,
      "content_type": "text/html",
      "is_menu_like": true
    },
    {
      "url": "http://www.levantinenyc.com/menus/office",
      "file": "menus/23bd5c6b-2464-4c4a-9d2e-6f15cf711989/office-lunch.html",
      "status": 200,
      "content_type": "text/html",
      "is_menu_like": true
    },
    {
      "url": "http://www.levantinenyc.com/menus/drinks",
      "file": "menus/23bd5c6b-2464-4c4a-9d2e-6f15cf711989/drinks.html",
      "status": 200,
      "content_type": "text/html",
      "is_menu_like": true
    }
  ],
  "errors": []
}