{
  "uuid": "b0d448c7-fd63-4467-831e-0638fb18e935",
  "name": "Lee's Villa",
  "website": "http://places.singleplatform.com/lees-villa/menu?ref=google",
  "found": true,
  "saved_files": [
    {
      "url": "http://places.singleplatform.com/lees-villa/menu?ref=google#all-menus",
      "file": "menus/b0d448c7-fd63-4467-831e-0638fb18e935/menu.html",
      "status": 200,
      "content_type": "text/html",
      "is_menu_like": true
    },
    {
      "url": "http://places.singleplatform.com/lees-villa/menu?ref=google",
      "file": "menus/b0d448c7-fd63-4467-831e-0638fb18e935/menu.html",
      "status": 200,
      "content_type": "text/html",
      "is_menu_like": true
    }
  ],
  "errors": []
}