{
  "uuid": "288e479a-8b43-415b-b5d5-22f78336b6da",
  "name": "Bardolino Pizza",
  "website": "http://orderbardolinopizza.com",
  "timestamp": "2025-12-08T13:46:14.604513+00:00",
  "found": true,
  "saved_files": [
    {
      "url": "http://orderbardolinopizza.com",
      "file": "menus/288e479a-8b43-415b-b5d5-22f78336b6da/menu.html",
      "status": 200,
      "content_type": "text/html",
      "is_menu_like": true
    },
    {
      "url": "http://orderbardolinopizza.com/index.php",
      "file": "menus/288e479a-8b43-415b-b5d5-22f78336b6da/index-php.html",
      "status": 200,
      "content_type": "text/html",
      "is_menu_like": true
    },
    {
      "url": "http://orderbardolinopizza.com/location.php",
      "file": "menus/288e479a-8b43-415b-b5d5-22f78336b6da/location-php.html",
      "status": 200,
      "content_type": "text/html",
      "is_menu_like": true
    },
    {
      "url": "http://orderbardolinopizza.com/menus",
      "file": "menus/288e479a-8b43-415b-b5d5-22f78336b6da/menus.html",
      "status": 200,
      "content_type": "text/html",
      "is_menu_like": true
    }
  ],
  "errors": [
    "blocked_by_robots:https://themenustar3.com/webspace/menus.php?code=orderbardolinopizza.com",
    "blocked_by_robots:https://themenustar3.com/webspace/rewards.php?code=orderbardolinopizza.com",
    "blocked_by_robots:https://themenustar3.com/webspace/orders.php?code=orderbardolinopizza.com",
    "error_page:http://orderbardolinopizza.com/menu:404",
    "error_page:http://orderbardolinopizza.com/our-menu:404",
    "error_page:http://orderbardolinopizza.com/our-menus:404",
    "error_page:http://orderbardolinopizza.com/food-menu:404",
    "error_page:http://orderbardolinopizza.com/food-menus:404",
    "error_page:http://orderbardolinopizza.com/dinner-menu:404",
    "error_page:http://orderbardolinopizza.com/lunch-menu:404",
    "error_page:http://orderbardolinopizza.com/brunch-menu:404",
    "error_page:http://orderbardolinopizza.com/breakfast-menu:404",
    "error_page:http://orderbardolinopizza.com/kids-menu:404",
    "error_page:http://orderbardolinopizza.com/kid-menu:404",
    "error_page:http://orderbardolinopizza.com/kids:404",
    "error_page:http://orderbardolinopizza.com/drinks-menu:404",
    "error_page:http://orderbardolinopizza.com/drink-menu:404",
    "error_page:http://orderbardolinopizza.com/beverages-menu:404",
    "error_page:http://orderbardolinopizza.com/beverage-menu:404",
    "error_page:http://orderbardolinopizza.com/wine-menu:404",
    "error_page:http://orderbardolinopizza.com/dessert-menu:404",
    "error_page:http://orderbardolinopizza.com/specials:404",
    "error_page:http://orderbardolinopizza.com/daily-specials:404",
    "error_page:http://orderbardolinopizza.com/today-specials:404",
    "error_page:http://orderbardolinopizza.com/buffet-menu:404",
    "error_page:http://orderbardolinopizza.com/takeaway-menu:404",
    "error_page:http://orderbardolinopizza.com/take-out-menu:404",
    "error_page:http://orderbardolinopizza.com/delivery-menu:404",
    "error_page:http://orderbardolinopizza.com/order-online/menu:404",
    "error_page:http://orderbardolinopizza.com/order/menu:404",
    "error_page:http://orderbardolinopizza.com/menu.html:404",
    "error_page:http://orderbardolinopizza.com/our-menu.html:404",
    "error_page:http://orderbardolinopizza.com/food-menu.html:404",
    "error_page:http://orderbardolinopizza.com/lunch-menu.html:404",
    "error_page:http://orderbardolinopizza.com/dinner-menu.html:404",
    "error_page:http://orderbardolinopizza.com/menu.pdf:404",
    "error_page:http://orderbardolinopizza.com/our-menu.pdf:404",
    "error_page:http://orderbardolinopizza.com/food-menu.pdf:404",
    "error_page:http://orderbardolinopizza.com/dinner-menu.pdf:404",
    "error_page:http://orderbardolinopizza.com/lunch-menu.pdf:404",
    "error_page:http://orderbardolinopizza.com/brunch-menu.pdf:404",
    "error_page:http://orderbardolinopizza.com/breakfast-menu.pdf:404",
    "error_page:http://orderbardolinopizza.com/kids-menu.pdf:404",
    "error_page:http://orderbardolinopizza.com/drinks-menu.pdf:404",
    "error_page:http://orderbardolinopizza.com/drink-menu.pdf:404",
    "error_page:http://orderbardolinopizza.com/takeaway-menu.pdf:404",
    "error_page:http://orderbardolinopizza.com/take-out-menu.pdf:404",
    "error_page:http://orderbardolinopizza.com/dessert-menu.pdf:404",
    "error_page:http://orderbardolinopizza.com/wine-menu.pdf:404",
    "error_page:http://orderbardolinopizza.com/specials.pdf:404",
    "error_page:http://orderbardolinopizza.com/buffet-menu.pdf:404",
    "error_page:http://orderbardolinopizza.com/wp-content/uploads/menu.pdf:404",
    "error_page:http://orderbardolinopizza.com/wp-content/uploads/menus.pdf:404",
    "error_page:http://orderbardolinopizza.com/wp-content/uploads/2023/menu.pdf:404",
    "error_page:http://orderbardolinopizza.com/wp-content/uploads/2024/menu.pdf:404",
    "error_page:http://orderbardolinopizza.com/wp-content/uploads/2022/menu.pdf:404",
    "error_page:http://orderbardolinopizza.com/files/menu.pdf:404",
    "error_page:http://orderbardolinopizza.com/uploads/menu.pdf:404",
    "error_page:http://orderbardolinopizza.com/download/menu.pdf:404",
    "error_page:http://orderbardolinopizza.com/documents/menu.pdf:404",
    "error_page:http://orderbardolinopizza.com/docs/menu.pdf:404",
    "error_page:http://orderbardolinopizza.com/menu/dinner:404",
    "error_page:http://orderbardolinopizza.com/menu/lunch:404",
    "error_page:http://orderbardolinopizza.com/menu/brunch:404",
    "error_page:http://orderbardolinopizza.com/menu/breakfast:404",
    "error_page:http://orderbardolinopizza.com/menu/drinks:404",
    "error_page:http://orderbardolinopizza.com/menu/beverages:404",
    "error_page:http://orderbardolinopizza.com/menu/kids:404",
    "error_page:http://orderbardolinopizza.com/menu/dessert:404",
    "error_page:http://orderbardolinopizza.com/menu/specials:404",
    "error_page:http://orderbardolinopizza.com/restaurant-menu:404",
    "error_page:http://orderbardolinopizza.com/the-menu:404",
    "error_page:http://orderbardolinopizza.com/menus-list:404",
    "error_page:http://orderbardolinopizza.com/full-menu:404",
    "error_page:http://orderbardolinopizza.com/complete-menu:404",
    "error_page:http://orderbardolinopizza.com/menu-card:404",
    "error_page:http://orderbardolinopizza.com/menu-list:404",
    "error_page:http://orderbardolinopizza.com/food:404",
    "error_page:http://orderbardolinopizza.com/eat:404",
    "error_page:http://orderbardolinopizza.com/order:404",
    "error_page:http://orderbardolinopizza.com/order-online:404"
  ]
}