{
  "uuid": "8e9f2d3d-5518-42bb-b459-90a02a80abef",
  "name": "Alice's Kitchen",
  "website": "https://www.aliceskitchen.net/",
  "timestamp": "2025-12-08T11:09:49.240257+00:00",
  "found": true,
  "saved_files": [
    {
      "url": "https://www.aliceskitchen.net/menu/specials",
      "file": "menus/8e9f2d3d-5518-42bb-b459-90a02a80abef/menu-specials.html",
      "status": 200,
      "content_type": "text/html",
      "is_menu_like": true
    }
  ],
  "errors": [
    "error_page:https://www.aliceskitchen.net/menu:429",
    "error_page:https://www.aliceskitchen.net/:429",
    "error_page:https://www.aliceskitchen.net/menus:429",
    "error_page:https://www.aliceskitchen.net/our-menu:429",
    "error_page:https://www.aliceskitchen.net/our-menus:429",
    "error_page:https://www.aliceskitchen.net/food-menu:429",
    "error_page:https://www.aliceskitchen.net/food-menus:429",
    "error_page:https://www.aliceskitchen.net/dinner-menu:429",
    "error_page:https://www.aliceskitchen.net/lunch-menu:429",
    "error_page:https://www.aliceskitchen.net/brunch-menu:429",
    "error_page:https://www.aliceskitchen.net/breakfast-menu:429",
    "error_page:https://www.aliceskitchen.net/kids-menu:429",
    "error_page:https://www.aliceskitchen.net/kid-menu:429",
    "error_page:https://www.aliceskitchen.net/kids:429",
    "error_page:https://www.aliceskitchen.net/drinks-menu:429",
    "error_page:https://www.aliceskitchen.net/drink-menu:404",
    "error_page:https://www.aliceskitchen.net/beverages-menu:404",
    "error_page:https://www.aliceskitchen.net/beverage-menu:404",
    "error_page:https://www.aliceskitchen.net/wine-menu:429",
    "error_page:https://www.aliceskitchen.net/dessert-menu:429",
    "error_page:https://www.aliceskitchen.net/specials:429",
    "error_page:https://www.aliceskitchen.net/daily-specials:429",
    "error_page:https://www.aliceskitchen.net/today-specials:429",
    "error_page:https://www.aliceskitchen.net/buffet-menu:429",
    "error_page:https://www.aliceskitchen.net/takeaway-menu:429",
    "error_page:https://www.aliceskitchen.net/take-out-menu:429",
    "error_page:https://www.aliceskitchen.net/delivery-menu:429",
    "error_page:https://www.aliceskitchen.net/order-online/menu:429",
    "error_page:https://www.aliceskitchen.net/order/menu:429",
    "error_page:https://www.aliceskitchen.net/menu.html:429",
    "error_page:https://www.aliceskitchen.net/menus.html:429",
    "error_page:https://www.aliceskitchen.net/our-menu.html:429",
    "error_page:https://www.aliceskitchen.net/food-menu.html:429",
    "error_page:https://www.aliceskitchen.net/lunch-menu.html:429",
    "error_page:https://www.aliceskitchen.net/dinner-menu.html:429",
    "error_page:https://www.aliceskitchen.net/menu.pdf:429",
    "error_page:https://www.aliceskitchen.net/menus.pdf:429",
    "error_page:https://www.aliceskitchen.net/our-menu.pdf:429",
    "error_page:https://www.aliceskitchen.net/food-menu.pdf:429",
    "error_page:https://www.aliceskitchen.net/dinner-menu.pdf:429",
    "error_page:https://www.aliceskitchen.net/lunch-menu.pdf:429",
    "error_page:https://www.aliceskitchen.net/brunch-menu.pdf:429",
    "error_page:https://www.aliceskitchen.net/breakfast-menu.pdf:429",
    "error_page:https://www.aliceskitchen.net/kids-menu.pdf:429",
    "error_page:https://www.aliceskitchen.net/drinks-menu.pdf:429",
    "error_page:https://www.aliceskitchen.net/drink-menu.pdf:429",
    "error_page:https://www.aliceskitchen.net/takeaway-menu.pdf:429",
    "error_page:https://www.aliceskitchen.net/take-out-menu.pdf:429",
    "error_page:https://www.aliceskitchen.net/dessert-menu.pdf:429",
    "error_page:https://www.aliceskitchen.net/wine-menu.pdf:429",
    "error_page:https://www.aliceskitchen.net/specials.pdf:429",
    "error_page:https://www.aliceskitchen.net/buffet-menu.pdf:429",
    "error_page:https://www.aliceskitchen.net/wp-content/uploads/menu.pdf:429",
    "error_page:https://www.aliceskitchen.net/wp-content/uploads/menus.pdf:429",
    "error_page:https://www.aliceskitchen.net/wp-content/uploads/2023/menu.pdf:429",
    "error_page:https://www.aliceskitchen.net/wp-content/uploads/2024/menu.pdf:429",
    "error_page:https://www.aliceskitchen.net/wp-content/uploads/2022/menu.pdf:429",
    "error_page:https://www.aliceskitchen.net/files/menu.pdf:429",
    "error_page:https://www.aliceskitchen.net/uploads/menu.pdf:429",
    "error_page:https://www.aliceskitchen.net/download/menu.pdf:429",
    "error_page:https://www.aliceskitchen.net/documents/menu.pdf:429",
    "error_page:https://www.aliceskitchen.net/docs/menu.pdf:429",
    "error_page:https://www.aliceskitchen.net/menu/dinner:429",
    "error_page:https://www.aliceskitchen.net/menu/lunch:429",
    "error_page:https://www.aliceskitchen.net/menu/brunch:429",
    "error_page:https://www.aliceskitchen.net/menu/breakfast:429",
    "error_page:https://www.aliceskitchen.net/menu/drinks:429",
    "error_page:https://www.aliceskitchen.net/menu/beverages:429",
    "error_page:https://www.aliceskitchen.net/menu/kids:429",
    "error_page:https://www.aliceskitchen.net/menu/dessert:429",
    "error_page:https://www.aliceskitchen.net/restaurant-menu:404",
    "error_page:https://www.aliceskitchen.net/the-menu:404",
    "error_page:https://www.aliceskitchen.net/menus-list:404",
    "error_page:https://www.aliceskitchen.net/full-menu:429",
    "error_page:https://www.aliceskitchen.net/complete-menu:429",
    "error_page:https://www.aliceskitchen.net/menu-card:429",
    "error_page:https://www.aliceskitchen.net/menu-list:429",
    "error_page:https://www.aliceskitchen.net/food:429",
    "error_page:https://www.aliceskitchen.net/eat:429",
    "error_page:https://www.aliceskitchen.net/order:429",
    "error_page:https://www.aliceskitchen.net/order-online:429"
  ]
}