{
  "uuid": "bdd8e7b1-bca1-4f52-b161-303adccf81b4",
  "name": "missKOREA BBQ",
  "website": "https://www.misskoreabbq.com",
  "timestamp": "2025-12-06T20:30:52.542053+00:00",
  "found": true,
  "saved_files": [
    {
      "url": "https://www.misskoreabbq.com",
      "file": "menus/bdd8e7b1-bca1-4f52-b161-303adccf81b4/menu.html",
      "status": 200,
      "content_type": "text/html",
      "is_menu_like": true
    },
    {
      "url": "https://www.ubereats.com/new-york/food-delivery/miss-korea-bbq-flatiron/oug6tIDbSRy4D0V0pUdEKw",
      "file": "menus/bdd8e7b1-bca1-4f52-b161-303adccf81b4/uber-eats.html",
      "status": 200,
      "content_type": "text/html",
      "is_menu_like": true
    }
  ],
  "errors": []
}