{
  "uuid": "8f9945d8-0388-4c06-a78a-82f876f07355",
  "name": "Taboonette",
  "website": "https://taboonette.com/",
  "timestamp": "2025-12-06T21:09:30.872222+00:00",
  "found": true,
  "saved_files": [
    {
      "url": "https://taboonette.com/menu/",
      "file": "menus/8f9945d8-0388-4c06-a78a-82f876f07355/menu.html",
      "status": 200,
      "content_type": "text/html",
      "is_menu_like": true
    },
    {
      "url": "https://taboonette.com/",
      "file": "menus/8f9945d8-0388-4c06-a78a-82f876f07355/menu.html",
      "status": 200,
      "content_type": "text/html",
      "is_menu_like": true
    }
  ],
  "errors": [
    "blocked_by_robots:https://taboonette.mobilebytes.com/",
    "fetch_failed:mailto:orders@taboonette.com:None:None"
  ]
}