{
  "uuid": "17907b0c-930f-4f44-91c7-1d467ec28649",
  "name": "Domino's",
  "website": "https://pizza.dominos.com/connecticut/mystic/242-greenmanville-ave",
  "timestamp": "2025-12-08T12:59:02.915529+00:00",
  "found": true,
  "saved_files": [
    {
      "url": "https://www.dominos.com/en/pages/order/menu#!/menu/category/drinks/",
      "file": "menus/17907b0c-930f-4f44-91c7-1d467ec28649/drinks.html",
      "status": 200,
      "content_type": "text/html",
      "is_menu_like": false
    },
    {
      "url": "https://www.dominos.com/menu",
      "file": "menus/17907b0c-930f-4f44-91c7-1d467ec28649/order-online.html",
      "status": 200,
      "content_type": "text/html",
      "is_menu_like": false
    },
    {
      "url": "https://www.dominos.com/en/pages/order/menu?utm_content=PDOT",
      "file": "menus/17907b0c-930f-4f44-91c7-1d467ec28649/menu.html",
      "status": 200,
      "content_type": "text/html",
      "is_menu_like": false
    },
    {
      "url": "https://www.dominos.com/en/pages/order/menu#!/menu/category/specialty-pizzas/",
      "file": "menus/17907b0c-930f-4f44-91c7-1d467ec28649/build-your-own.html",
      "status": 200,
      "content_type": "text/html",
      "is_menu_like": false
    },
    {
      "url": "https://www.dominos.com/en/pages/order/menu#!/menu/category/breadsandOvenBakedDips/",
      "file": "menus/17907b0c-930f-4f44-91c7-1d467ec28649/breads.html",
      "status": 200,
      "content_type": "text/html",
      "is_menu_like": false
    }
  ],
  "errors": []
}