{
  "uuid": "56352b5f-aaa2-461d-8c64-d1bdd1a4b2fd",
  "name": "Amelia's Bistro",
  "website": "https://www.ameliabistro.com/",
  "found": true,
  "saved_files": [
    {
      "url": "https://www.ameliabistro.com/menu",
      "file": "menus/56352b5f-aaa2-461d-8c64-d1bdd1a4b2fd/menu.html",
      "status": 200,
      "content_type": "text/html",
      "is_menu_like": true
    },
    {
      "url": "https://www.ameliabistro.com/",
      "file": "menus/56352b5f-aaa2-461d-8c64-d1bdd1a4b2fd/menu.html",
      "status": 200,
      "content_type": "text/html",
      "is_menu_like": true
    }
  ],
  "errors": []
}