{
  "uuid": "1793ec2f-83a5-47a6-9f01-e9e435dfcb45",
  "name": "Lakruwana",
  "website": "http://www.lakruwana.com/",
  "timestamp": "2025-12-08T11:00:04.247692+00:00",
  "found": true,
  "saved_files": [
    {
      "url": "http://www.lakruwana.com/",
      "file": "menus/1793ec2f-83a5-47a6-9f01-e9e435dfcb45/menu.html",
      "status": 200,
      "content_type": "text/html",
      "is_menu_like": true
    },
    {
      "url": "http://www.lakruwana.com/menu",
      "file": "menus/1793ec2f-83a5-47a6-9f01-e9e435dfcb45/menu.html",
      "status": 200,
      "content_type": "text/html",
      "is_menu_like": true
    }
  ],
  "errors": [
    "error_page:http://www.lakruwana.com/menus:404",
    "error_page:http://www.lakruwana.com/our-menu:404",
    "error_page:http://www.lakruwana.com/our-menus:404",
    "error_page:http://www.lakruwana.com/food-menu:404",
    "error_page:http://www.lakruwana.com/food-menus:404",
    "error_page:http://www.lakruwana.com/dinner-menu:404",
    "error_page:http://www.lakruwana.com/lunch-menu:404",
    "error_page:http://www.lakruwana.com/brunch-menu:404",
    "error_page:http://www.lakruwana.com/breakfast-menu:404",
    "error_page:http://www.lakruwana.com/kids-menu:404",
    "error_page:http://www.lakruwana.com/kid-menu:404",
    "error_page:http://www.lakruwana.com/kids:404",
    "error_page:http://www.lakruwana.com/drinks-menu:404",
    "error_page:http://www.lakruwana.com/drink-menu:404",
    "error_page:http://www.lakruwana.com/beverages-menu:404",
    "error_page:http://www.lakruwana.com/beverage-menu:404",
    "error_page:http://www.lakruwana.com/wine-menu:404",
    "error_page:http://www.lakruwana.com/dessert-menu:404",
    "error_page:http://www.lakruwana.com/specials:404",
    "error_page:http://www.lakruwana.com/daily-specials:404",
    "error_page:http://www.lakruwana.com/today-specials:404",
    "error_page:http://www.lakruwana.com/buffet-menu:404",
    "error_page:http://www.lakruwana.com/takeaway-menu:404",
    "error_page:http://www.lakruwana.com/take-out-menu:404",
    "error_page:http://www.lakruwana.com/delivery-menu:404",
    "error_page:http://www.lakruwana.com/order-online/menu:404",
    "error_page:http://www.lakruwana.com/order/menu:404",
    "error_page:http://www.lakruwana.com/menu.html:404",
    "error_page:http://www.lakruwana.com/menus.html:404",
    "error_page:http://www.lakruwana.com/our-menu.html:404",
    "error_page:http://www.lakruwana.com/food-menu.html:404",
    "error_page:http://www.lakruwana.com/lunch-menu.html:404",
    "error_page:http://www.lakruwana.com/dinner-menu.html:404",
    "error_page:http://www.lakruwana.com/menu.pdf:404",
    "error_page:http://www.lakruwana.com/menus.pdf:404",
    "error_page:http://www.lakruwana.com/our-menu.pdf:404",
    "error_page:http://www.lakruwana.com/food-menu.pdf:404",
    "error_page:http://www.lakruwana.com/dinner-menu.pdf:404",
    "error_page:http://www.lakruwana.com/lunch-menu.pdf:404",
    "error_page:http://www.lakruwana.com/brunch-menu.pdf:404",
    "error_page:http://www.lakruwana.com/breakfast-menu.pdf:404",
    "error_page:http://www.lakruwana.com/kids-menu.pdf:404",
    "error_page:http://www.lakruwana.com/drinks-menu.pdf:404",
    "error_page:http://www.lakruwana.com/drink-menu.pdf:404",
    "error_page:http://www.lakruwana.com/takeaway-menu.pdf:404",
    "error_page:http://www.lakruwana.com/take-out-menu.pdf:404",
    "error_page:http://www.lakruwana.com/dessert-menu.pdf:404",
    "error_page:http://www.lakruwana.com/wine-menu.pdf:404",
    "error_page:http://www.lakruwana.com/specials.pdf:404",
    "error_page:http://www.lakruwana.com/buffet-menu.pdf:404",
    "error_page:http://www.lakruwana.com/wp-content/uploads/menu.pdf:404",
    "error_page:http://www.lakruwana.com/wp-content/uploads/menus.pdf:404",
    "error_page:http://www.lakruwana.com/wp-content/uploads/2023/menu.pdf:404",
    "error_page:http://www.lakruwana.com/wp-content/uploads/2024/menu.pdf:404",
    "error_page:http://www.lakruwana.com/wp-content/uploads/2022/menu.pdf:404",
    "error_page:http://www.lakruwana.com/files/menu.pdf:404",
    "error_page:http://www.lakruwana.com/uploads/menu.pdf:404",
    "error_page:http://www.lakruwana.com/download/menu.pdf:404",
    "error_page:http://www.lakruwana.com/documents/menu.pdf:404",
    "error_page:http://www.lakruwana.com/docs/menu.pdf:404",
    "error_page:http://www.lakruwana.com/menu/dinner:404",
    "error_page:http://www.lakruwana.com/menu/lunch:404",
    "error_page:http://www.lakruwana.com/menu/brunch:404",
    "error_page:http://www.lakruwana.com/menu/breakfast:404",
    "error_page:http://www.lakruwana.com/menu/drinks:404",
    "error_page:http://www.lakruwana.com/menu/beverages:404",
    "error_page:http://www.lakruwana.com/menu/kids:404",
    "error_page:http://www.lakruwana.com/menu/dessert:404",
    "error_page:http://www.lakruwana.com/menu/specials:404",
    "error_page:http://www.lakruwana.com/restaurant-menu:404",
    "error_page:http://www.lakruwana.com/the-menu:404",
    "error_page:http://www.lakruwana.com/menus-list:404",
    "error_page:http://www.lakruwana.com/full-menu:404",
    "error_page:http://www.lakruwana.com/complete-menu:404",
    "error_page:http://www.lakruwana.com/menu-card:404",
    "error_page:http://www.lakruwana.com/menu-list:404",
    "error_page:http://www.lakruwana.com/food:404",
    "error_page:http://www.lakruwana.com/eat:404",
    "error_page:http://www.lakruwana.com/order:404",
    "error_page:http://www.lakruwana.com/order-online:404"
  ]
}