{
  "uuid": "62748ca1-be7b-4c27-a8ce-c6adbc7e3a12",
  "name": "MayRee",
  "website": "https://www.mayreenyc.com/",
  "found": true,
  "saved_files": [
    {
      "url": "https://www.mayreenyc.com/menu",
      "file": "menus/62748ca1-be7b-4c27-a8ce-c6adbc7e3a12/menu.html",
      "status": 200,
      "content_type": "text/html",
      "is_menu_like": true
    },
    {
      "url": "https://www.mayreenyc.com/",
      "file": "menus/62748ca1-be7b-4c27-a8ce-c6adbc7e3a12/menu.html",
      "status": 200,
      "content_type": "text/html",
      "is_menu_like": true
    }
  ],
  "errors": []
}