{
  "uuid": "e560ea45-09d3-4b9e-9524-f0220825e4b1",
  "name": "Chelsea Square Restaurant",
  "website": "https://www.chelseasquarediner.com/",
  "timestamp": "2025-12-06T14:25:02.858796+00:00",
  "found": true,
  "saved_files": [
    {
      "url": "https://www.chelseasquarediner.com/menu/",
      "file": "menus/e560ea45-09d3-4b9e-9524-f0220825e4b1/menu.html",
      "status": 200,
      "content_type": "text/html",
      "is_menu_like": true
    },
    {
      "url": "https://www.chelseasquarediner.com/",
      "file": "menus/e560ea45-09d3-4b9e-9524-f0220825e4b1/menu.html",
      "status": 200,
      "content_type": "text/html",
      "is_menu_like": true
    },
    {
      "url": "https://itunes.apple.com/us/app/delivery.com/id435168129?mt=8",
      "file": "menus/e560ea45-09d3-4b9e-9524-f0220825e4b1/start-your-order-on-the-app.html",
      "status": 200,
      "content_type": "text/html",
      "is_menu_like": true
    }
  ],
  "errors": []
}