{
  "uuid": "1b948b71-e899-45e6-a61e-379d1f65461e",
  "name": "McDonald's",
  "website": "https://www.mcdonalds.com/us/en-us/location/2793.html",
  "timestamp": "2025-12-08T13:23:24.187569+00:00",
  "found": true,
  "saved_files": [
    {
      "url": "https://www.mcdonalds.com/us/en-us/full-menu/drinks.html",
      "file": "menus/1b948b71-e899-45e6-a61e-379d1f65461e/beverages.html",
      "status": 200,
      "content_type": "text/html",
      "is_menu_like": true
    },
    {
      "url": "https://www.mcdonalds.com/us/en-us/full-menu.html",
      "file": "menus/1b948b71-e899-45e6-a61e-379d1f65461e/view-full-menu.html",
      "status": 200,
      "content_type": "text/html",
      "is_menu_like": true
    },
    {
      "url": "https://www.mcdonalds.com/us/en-us/full-menu/extra-value-meals-menu.html",
      "file": "menus/1b948b71-e899-45e6-a61e-379d1f65461e/extra-value-meals.html",
      "status": 200,
      "content_type": "text/html",
      "is_menu_like": true
    },
    {
      "url": "https://www.mcdonalds.com/us/en-us/full-menu/mcvalue-menu.html",
      "file": "menus/1b948b71-e899-45e6-a61e-379d1f65461e/mcvalue.html",
      "status": 200,
      "content_type": "text/html",
      "is_menu_like": true
    },
    {
      "url": "https://www.mcdonalds.com/us/en-us/location/2793.html",
      "file": "menus/1b948b71-e899-45e6-a61e-379d1f65461e/2793-html.html",
      "status": 200,
      "content_type": "text/html",
      "is_menu_like": true
    }
  ],
  "errors": []
}