{
  "uuid": "b1361b02-f322-41e7-9c53-e1eaa43e56e3",
  "name": "POST",
  "website": "https://www.post-nyc.com/",
  "timestamp": "2025-12-08T11:17:07.448032+00:00",
  "found": true,
  "saved_files": [
    {
      "url": "https://resy.com/cities/ny/post",
      "file": "menus/b1361b02-f322-41e7-9c53-e1eaa43e56e3/book-your-post-reservation-on-resy.html",
      "status": 200,
      "content_type": "text/html",
      "is_menu_like": true
    }
  ],
  "errors": [
    "error_page:https://www.post-nyc.com/menu:404",
    "error_page:https://www.post-nyc.com/menus:404",
    "error_page:https://www.post-nyc.com/our-menu:404",
    "error_page:https://www.post-nyc.com/our-menus:404",
    "error_page:https://www.post-nyc.com/food-menu:404",
    "error_page:https://www.post-nyc.com/food-menus:404",
    "error_page:https://www.post-nyc.com/dinner-menu:404",
    "error_page:https://www.post-nyc.com/lunch-menu:404",
    "error_page:https://www.post-nyc.com/brunch-menu:404",
    "error_page:https://www.post-nyc.com/breakfast-menu:404",
    "error_page:https://www.post-nyc.com/kids-menu:404",
    "error_page:https://www.post-nyc.com/kid-menu:404",
    "error_page:https://www.post-nyc.com/kids:404",
    "error_page:https://www.post-nyc.com/drinks-menu:404",
    "error_page:https://www.post-nyc.com/drink-menu:404",
    "error_page:https://www.post-nyc.com/beverages-menu:404",
    "error_page:https://www.post-nyc.com/beverage-menu:404",
    "error_page:https://www.post-nyc.com/wine-menu:404",
    "error_page:https://www.post-nyc.com/dessert-menu:404",
    "error_page:https://www.post-nyc.com/specials:404",
    "error_page:https://www.post-nyc.com/daily-specials:404",
    "error_page:https://www.post-nyc.com/today-specials:404",
    "error_page:https://www.post-nyc.com/buffet-menu:404",
    "error_page:https://www.post-nyc.com/takeaway-menu:404",
    "error_page:https://www.post-nyc.com/take-out-menu:404",
    "error_page:https://www.post-nyc.com/delivery-menu:404",
    "error_page:https://www.post-nyc.com/order-online/menu:404",
    "error_page:https://www.post-nyc.com/order/menu:404",
    "error_page:https://www.post-nyc.com/menu.html:404",
    "error_page:https://www.post-nyc.com/menus.html:404",
    "error_page:https://www.post-nyc.com/our-menu.html:404",
    "error_page:https://www.post-nyc.com/food-menu.html:404",
    "error_page:https://www.post-nyc.com/lunch-menu.html:404",
    "error_page:https://www.post-nyc.com/dinner-menu.html:404",
    "error_page:https://www.post-nyc.com/menu.pdf:404",
    "error_page:https://www.post-nyc.com/menus.pdf:404",
    "error_page:https://www.post-nyc.com/our-menu.pdf:404",
    "error_page:https://www.post-nyc.com/food-menu.pdf:404",
    "error_page:https://www.post-nyc.com/dinner-menu.pdf:404",
    "error_page:https://www.post-nyc.com/lunch-menu.pdf:404",
    "error_page:https://www.post-nyc.com/brunch-menu.pdf:404",
    "error_page:https://www.post-nyc.com/breakfast-menu.pdf:404",
    "error_page:https://www.post-nyc.com/kids-menu.pdf:404",
    "error_page:https://www.post-nyc.com/drinks-menu.pdf:404",
    "error_page:https://www.post-nyc.com/drink-menu.pdf:404",
    "error_page:https://www.post-nyc.com/takeaway-menu.pdf:404",
    "error_page:https://www.post-nyc.com/take-out-menu.pdf:404",
    "error_page:https://www.post-nyc.com/dessert-menu.pdf:404",
    "error_page:https://www.post-nyc.com/wine-menu.pdf:404",
    "error_page:https://www.post-nyc.com/specials.pdf:404",
    "error_page:https://www.post-nyc.com/buffet-menu.pdf:404",
    "error_page:https://www.post-nyc.com/wp-content/uploads/menu.pdf:404",
    "error_page:https://www.post-nyc.com/wp-content/uploads/menus.pdf:404",
    "error_page:https://www.post-nyc.com/wp-content/uploads/2023/menu.pdf:404",
    "error_page:https://www.post-nyc.com/wp-content/uploads/2024/menu.pdf:404",
    "error_page:https://www.post-nyc.com/wp-content/uploads/2022/menu.pdf:404",
    "error_page:https://www.post-nyc.com/files/menu.pdf:404",
    "error_page:https://www.post-nyc.com/uploads/menu.pdf:404",
    "error_page:https://www.post-nyc.com/download/menu.pdf:404",
    "error_page:https://www.post-nyc.com/documents/menu.pdf:404",
    "error_page:https://www.post-nyc.com/docs/menu.pdf:404",
    "error_page:https://www.post-nyc.com/menu/dinner:404",
    "error_page:https://www.post-nyc.com/menu/lunch:404",
    "error_page:https://www.post-nyc.com/menu/brunch:404",
    "error_page:https://www.post-nyc.com/menu/breakfast:404",
    "error_page:https://www.post-nyc.com/menu/drinks:404",
    "error_page:https://www.post-nyc.com/menu/beverages:404",
    "error_page:https://www.post-nyc.com/menu/kids:404",
    "error_page:https://www.post-nyc.com/menu/dessert:404",
    "error_page:https://www.post-nyc.com/menu/specials:404",
    "error_page:https://www.post-nyc.com/restaurant-menu:404",
    "error_page:https://www.post-nyc.com/the-menu:404",
    "error_page:https://www.post-nyc.com/menus-list:404",
    "error_page:https://www.post-nyc.com/full-menu:404",
    "error_page:https://www.post-nyc.com/complete-menu:404",
    "error_page:https://www.post-nyc.com/menu-card:404",
    "error_page:https://www.post-nyc.com/menu-list:404",
    "error_page:https://www.post-nyc.com/food:404",
    "error_page:https://www.post-nyc.com/eat:404",
    "error_page:https://www.post-nyc.com/order:404",
    "error_page:https://www.post-nyc.com/order-online:404"
  ]
}