{
  "uuid": "62091172-63e8-4fed-b4aa-81c28e0a451c",
  "name": "El Barrio Burritos",
  "website": "https://elbarriobk.com/",
  "timestamp": "2025-12-08T13:03:48.107312+00:00",
  "found": true,
  "saved_files": [
    {
      "url": "https://elbarriobk.com/",
      "file": "menus/62091172-63e8-4fed-b4aa-81c28e0a451c/menu.html",
      "status": 200,
      "content_type": "text/html",
      "is_menu_like": true
    },
    {
      "url": "https://elbarriobk.com/specials",
      "file": "menus/62091172-63e8-4fed-b4aa-81c28e0a451c/specials.html",
      "status": 200,
      "content_type": "text/html",
      "is_menu_like": true
    },
    {
      "url": "https://elbarriobk.com/menu/specials",
      "file": "menus/62091172-63e8-4fed-b4aa-81c28e0a451c/menu-specials.html",
      "status": 200,
      "content_type": "text/html",
      "is_menu_like": true
    }
  ],
  "errors": [
    "error_page:https://direct.chownow.com/order/2394/locations/3121:403",
    "error_page:https://direct.chownow.com/direct/2394/locations/3121:403",
    "error_page:https://elbarriobk.com/menu:404",
    "error_page:https://elbarriobk.com/menus:404",
    "error_page:https://elbarriobk.com/our-menu:404",
    "error_page:https://elbarriobk.com/our-menus:404",
    "error_page:https://elbarriobk.com/food-menu:404",
    "error_page:https://elbarriobk.com/food-menus:404",
    "error_page:https://elbarriobk.com/dinner-menu:404",
    "error_page:https://elbarriobk.com/lunch-menu:404",
    "error_page:https://elbarriobk.com/brunch-menu:404",
    "error_page:https://elbarriobk.com/breakfast-menu:404",
    "error_page:https://elbarriobk.com/kids-menu:404",
    "error_page:https://elbarriobk.com/kid-menu:404",
    "error_page:https://elbarriobk.com/kids:404",
    "error_page:https://elbarriobk.com/drinks-menu:404",
    "error_page:https://elbarriobk.com/drink-menu:404",
    "error_page:https://elbarriobk.com/beverages-menu:404",
    "error_page:https://elbarriobk.com/beverage-menu:404",
    "error_page:https://elbarriobk.com/wine-menu:404",
    "error_page:https://elbarriobk.com/dessert-menu:404",
    "error_page:https://elbarriobk.com/daily-specials:404",
    "error_page:https://elbarriobk.com/today-specials:404",
    "error_page:https://elbarriobk.com/buffet-menu:404",
    "error_page:https://elbarriobk.com/takeaway-menu:404",
    "error_page:https://elbarriobk.com/take-out-menu:404",
    "error_page:https://elbarriobk.com/delivery-menu:404",
    "error_page:https://elbarriobk.com/order-online/menu:404",
    "error_page:https://elbarriobk.com/order/menu:404",
    "error_page:https://elbarriobk.com/menu.html:404",
    "error_page:https://elbarriobk.com/menus.html:404",
    "error_page:https://elbarriobk.com/our-menu.html:404",
    "error_page:https://elbarriobk.com/food-menu.html:404",
    "error_page:https://elbarriobk.com/lunch-menu.html:404",
    "error_page:https://elbarriobk.com/dinner-menu.html:404",
    "error_page:https://elbarriobk.com/menu.pdf:404",
    "error_page:https://elbarriobk.com/menus.pdf:404",
    "error_page:https://elbarriobk.com/our-menu.pdf:404",
    "error_page:https://elbarriobk.com/food-menu.pdf:404",
    "error_page:https://elbarriobk.com/dinner-menu.pdf:404",
    "error_page:https://elbarriobk.com/lunch-menu.pdf:404",
    "error_page:https://elbarriobk.com/brunch-menu.pdf:404",
    "error_page:https://elbarriobk.com/breakfast-menu.pdf:404",
    "error_page:https://elbarriobk.com/kids-menu.pdf:404",
    "error_page:https://elbarriobk.com/drinks-menu.pdf:404",
    "error_page:https://elbarriobk.com/drink-menu.pdf:404",
    "error_page:https://elbarriobk.com/takeaway-menu.pdf:404",
    "error_page:https://elbarriobk.com/take-out-menu.pdf:404",
    "error_page:https://elbarriobk.com/dessert-menu.pdf:404",
    "error_page:https://elbarriobk.com/wine-menu.pdf:404",
    "error_page:https://elbarriobk.com/specials.pdf:404",
    "error_page:https://elbarriobk.com/buffet-menu.pdf:404",
    "error_page:https://elbarriobk.com/wp-content/uploads/menu.pdf:404",
    "error_page:https://elbarriobk.com/wp-content/uploads/menus.pdf:404",
    "error_page:https://elbarriobk.com/wp-content/uploads/2023/menu.pdf:404",
    "error_page:https://elbarriobk.com/wp-content/uploads/2024/menu.pdf:404",
    "error_page:https://elbarriobk.com/wp-content/uploads/2022/menu.pdf:404",
    "error_page:https://elbarriobk.com/files/menu.pdf:404",
    "error_page:https://elbarriobk.com/uploads/menu.pdf:404",
    "error_page:https://elbarriobk.com/download/menu.pdf:404",
    "error_page:https://elbarriobk.com/documents/menu.pdf:404",
    "error_page:https://elbarriobk.com/docs/menu.pdf:404",
    "error_page:https://elbarriobk.com/menu/dinner:404",
    "error_page:https://elbarriobk.com/menu/lunch:404",
    "error_page:https://elbarriobk.com/menu/brunch:404",
    "fetch_failed:https://elbarriobk.com/menu/breakfast:None:None",
    "fetch_failed:https://elbarriobk.com/menu/drinks:None:None",
    "error_page:https://elbarriobk.com/menu/beverages:404",
    "error_page:https://elbarriobk.com/menu/kids:404",
    "error_page:https://elbarriobk.com/menu/dessert:404",
    "error_page:https://elbarriobk.com/restaurant-menu:404",
    "error_page:https://elbarriobk.com/the-menu:404",
    "error_page:https://elbarriobk.com/menus-list:404",
    "error_page:https://elbarriobk.com/full-menu:404",
    "error_page:https://elbarriobk.com/complete-menu:404",
    "error_page:https://elbarriobk.com/menu-card:404",
    "error_page:https://elbarriobk.com/menu-list:404",
    "error_page:https://elbarriobk.com/food:404",
    "error_page:https://elbarriobk.com/eat:404",
    "error_page:https://elbarriobk.com/order:404",
    "error_page:https://elbarriobk.com/order-online:404"
  ]
}