{
  "uuid": "10710338-3fcc-4cc2-9717-8b313ad8f0ee",
  "name": "Woodside Cafe",
  "website": "https://www.woodsidecafeny.com/",
  "timestamp": "2025-12-06T21:10:46.611706+00:00",
  "found": true,
  "saved_files": [
    {
      "url": "https://www.woodsidecafeny.com/",
      "file": "menus/10710338-3fcc-4cc2-9717-8b313ad8f0ee/menu.html",
      "status": 200,
      "content_type": "text/html",
      "is_menu_like": true
    },
    {
      "url": "https://88restaurants.com/1116/online_orders/new",
      "file": "menus/10710338-3fcc-4cc2-9717-8b313ad8f0ee/order-online.html",
      "status": 200,
      "content_type": "text/html",
      "is_menu_like": true
    }
  ],
  "errors": []
}