{
  "uuid": "f13bb1ff-6734-4e3b-98e5-01fd927ddd34",
  "name": "Coszcal de Allende",
  "website": "https://coszcal.com",
  "timestamp": "2025-12-08T23:20:56.150358+00:00",
  "found": true,
  "saved_files": [
    {
      "url": "https://coszcal.com/wp-content/uploads/2019/12/hhol12.pdf",
      "file": "menus/f13bb1ff-6734-4e3b-98e5-01fd927ddd34/happy-hour-menu.pdf",
      "status": 200,
      "content_type": "application/pdf",
      "is_menu_like": true,
      "source": "official"
    },
    {
      "url": "https://coszcal.com/menu/",
      "file": "menus/f13bb1ff-6734-4e3b-98e5-01fd927ddd34/see-our-menu.html",
      "status": 200,
      "content_type": "text/html",
      "is_menu_like": true,
      "source": "official"
    },
    {
      "url": "https://coszcal.com/wp-content/uploads/2019/12/on_ls_1.pdf",
      "file": "menus/f13bb1ff-6734-4e3b-98e5-01fd927ddd34/lunch-menu.pdf",
      "status": 200,
      "content_type": "application/pdf",
      "is_menu_like": true,
      "source": "official"
    },
    {
      "url": "https://coszcal.com/wp-content/uploads/2019/12/on_bb1.pdf",
      "file": "menus/f13bb1ff-6734-4e3b-98e5-01fd927ddd34/brunch-menu.pdf",
      "status": 200,
      "content_type": "application/pdf",
      "is_menu_like": true,
      "source": "official"
    },
    {
      "url": "https://coszcal.com",
      "file": "menus/f13bb1ff-6734-4e3b-98e5-01fd927ddd34/menu.html",
      "status": 200,
      "content_type": "text/html",
      "is_menu_like": true,
      "source": "official"
    },
    {
      "url": "https://coszcal.com/menu",
      "file": "menus/f13bb1ff-6734-4e3b-98e5-01fd927ddd34/menu.html",
      "status": 200,
      "content_type": "text/html",
      "is_menu_like": true,
      "source": "official"
    },
    {
      "url": "https://coszcal.com/order-online/menu",
      "file": "menus/f13bb1ff-6734-4e3b-98e5-01fd927ddd34/order-online-menu.html",
      "status": 200,
      "content_type": "text/html",
      "is_menu_like": true,
      "source": "official"
    },
    {
      "url": "https://coszcal.com/order/menu",
      "file": "menus/f13bb1ff-6734-4e3b-98e5-01fd927ddd34/order-menu.html",
      "status": 200,
      "content_type": "text/html",
      "is_menu_like": true,
      "source": "official"
    }
  ],
  "errors": [
    "error_page:https://coszcaldeallende.orders2me.com/order-now:403",
    "error_page:https://orders2.me/:403"
  ],
  "sources": [
    "official"
  ]
}