{
  "uuid": "52cc4a03-727c-4598-8b03-2a23c997fb34",
  "name": "Little Purity",
  "website": "https://littlepurity.shop/",
  "timestamp": "2025-12-06T14:25:30.844030+00:00",
  "found": true,
  "saved_files": [
    {
      "url": "https://little-purity.foodjoyy.net/menu",
      "file": "menus/52cc4a03-727c-4598-8b03-2a23c997fb34/menu.html",
      "status": 200,
      "content_type": "text/html",
      "is_menu_like": true
    },
    {
      "url": "https://littlepurity.shop/",
      "file": "menus/52cc4a03-727c-4598-8b03-2a23c997fb34/menu.html",
      "status": 200,
      "content_type": "text/html",
      "is_menu_like": true
    },
    {
      "url": "https://little-purity.foodjoyy.net/",
      "file": "menus/52cc4a03-727c-4598-8b03-2a23c997fb34/little-purity.html",
      "status": 200,
      "content_type": "text/html",
      "is_menu_like": true
    },
    {
      "url": "https://little-purity.foodjoyy.net/#about",
      "file": "menus/52cc4a03-727c-4598-8b03-2a23c997fb34/about.html",
      "status": 200,
      "content_type": "text/html",
      "is_menu_like": true
    },
    {
      "url": "https://little-purity.foodjoyy.net/#locations",
      "file": "menus/52cc4a03-727c-4598-8b03-2a23c997fb34/locations.html",
      "status": 200,
      "content_type": "text/html",
      "is_menu_like": true
    }
  ],
  "errors": []
}