{
  "uuid": "c109a39b-94db-458c-b4f7-86e80e2b29b9",
  "name": "Dunkin'",
  "website": "https://locations.dunkindonuts.com/en/ny/bronx/2-e-kingsbridge-ave/332798",
  "timestamp": "2025-12-08T13:40:16.922779+00:00",
  "found": true,
  "saved_files": [
    {
      "url": "https://www.grubhub.com/food/dunkin",
      "file": "menus/c109a39b-94db-458c-b4f7-86e80e2b29b9/order-now.html",
      "status": 200,
      "content_type": "text/html",
      "is_menu_like": true
    },
    {
      "url": "https://www.ubereats.com/brand/dunkin-donuts",
      "file": "menus/c109a39b-94db-458c-b4f7-86e80e2b29b9/order-now.html",
      "status": 200,
      "content_type": "text/html",
      "is_menu_like": true
    },
    {
      "url": "https://www.dunkindonuts.com/en/menu",
      "file": "menus/c109a39b-94db-458c-b4f7-86e80e2b29b9/menu.html",
      "status": 200,
      "content_type": "text/html",
      "is_menu_like": true
    },
    {
      "url": "https://locations.dunkindonuts.com/en/ny/bronx/2-e-kingsbridge-ave/332798",
      "file": "menus/c109a39b-94db-458c-b4f7-86e80e2b29b9/332798.html",
      "status": 200,
      "content_type": "text/html",
      "is_menu_like": true
    },
    {
      "url": "https://www.dunkindonuts.com/en/mobile-app",
      "file": "menus/c109a39b-94db-458c-b4f7-86e80e2b29b9/order-now.html",
      "status": 200,
      "content_type": "text/html",
      "is_menu_like": true
    }
  ],
  "errors": [
    "error_page:https://www.doordash.com/business/Dunkin--436529:403"
  ]
}